epyk_flask/__init__.py
epyk_flask/server_engine.py
epyk_flask/cli/__init__.py
epyk_flask/cli/cli.py
epyk_flask/cli/project_structure.py
epyk_flask/export/__init__.py
epyk_flask/export/env/__init__.py
epyk_flask/export/server/__init__.py
epyk_flask/export/server/app.py
epyk_flask/export/server/basic_endpoints.py
epyk_flask/export/server/index.py
epyk_flask/export/server/websocket_endpoints.py
epyk_flask-1.0.4.dist-info/LICENSE
epyk_flask-1.0.4.dist-info/METADATA
epyk_flask-1.0.4.dist-info/WHEEL
epyk_flask-1.0.4.dist-info/entry_points.txt
epyk_flask-1.0.4.dist-info/top_level.txt
epyk_flask-1.0.4.dist-info/RECORD
