Metadata-Version: 2.1
Name: epyk-flask
Version: 1.0.4
Summary: UNKNOWN
Home-page: https://github.com/epykure/epyk-flask
Author: epykure
Author-email: epykure@gmail.com
License: UNKNOWN
Platform: UNKNOWN
Classifier: Programming Language :: Python :: 3
Classifier: Programming Language :: Python :: 2.7
Classifier: License :: OSI Approved :: GNU General Public License (GPL)
Classifier: Operating System :: OS Independent
Requires-Python: >=2.7
Requires-Dist: flask
Requires-Dist: pyyaml
Requires-Dist: epyk
